{"version":1,"resource":"file:///home/jesus/portafolio_astro/square-series/src/layouts/Layout.astro","entries":[{"id":"ddtw.astro","timestamp":1752685364641},{"id":"CsOS.astro","timestamp":1752686187654},{"id":"nCzB.astro","timestamp":1752686233125},{"id":"99dM.astro","timestamp":1752686643146},{"id":"Za0O.astro","timestamp":1752686710092},{"id":"wE1d.astro","timestamp":1752686975872},{"id":"gT46.astro","timestamp":1752687667824},{"id":"wOH2.astro","timestamp":1752688617735},{"id":"g1wG.astro","timestamp":1752688707256}]}